dvrip/__init__.py
dvrip/__main__.py
dvrip/_version.py
dvrip/_version_lock.py
dvrip/discover.py
dvrip/errors.py
dvrip/info.py
dvrip/io.py
dvrip/login.py
dvrip/message.py
dvrip/monitor.py
dvrip/operation.py
dvrip/packet.py
dvrip/playback.py
dvrip/search.py
dvrip/typing.py
dvrip-0.0.3.data/scripts/dvrip_test
dvrip-0.0.3.dist-info/LICENSE
dvrip-0.0.3.dist-info/METADATA
dvrip-0.0.3.dist-info/WHEEL
dvrip-0.0.3.dist-info/entry_points.txt
dvrip-0.0.3.dist-info/top_level.txt
dvrip-0.0.3.dist-info/RECORD
