Metadata-Version: 2.1
Name: dvrip
Version: 0.0.3
Summary: DVRIP (Xiongmai, XMEye, Sofia protocol) library and tools
Requires-Dist: typing-inspect (<0.5,>=0.4)
Provides-Extra: dvr-find
Requires-Dist: dateparser ; extra == 'dvr-find'
Requires-Dist: humanize ; extra == 'dvr-find'
Provides-Extra: dvr-time
Requires-Dist: dateparser ; extra == 'dvr-time'
